compile_cache/__init__.py
compile_cache/compile_cache.py
baseten_compile_cache-0.1.1.dist-info/METADATA
baseten_compile_cache-0.1.1.dist-info/WHEEL
baseten_compile_cache-0.1.1.dist-info/top_level.txt
baseten_compile_cache-0.1.1.dist-info/RECORD
