Metadata-Version: 2.4
Name: baseten-compile-cache
Version: 0.1.1
Summary: Simple compile cache utilities for Baseten's development environment.
Author-email: Fred Liu <fredliu876@gmail.com>
License: MIT
Project-URL: Homepage, https://github.com/basetenlabs/compile_cache
Project-URL: Issues, https://github.com/basetenlabs/compile_cache/issues
Classifier: Programming Language :: Python :: 3
Classifier: License :: OSI Approved :: MIT License
Classifier: Operating System :: OS Independent
Requires-Python: >=3.8
